MANIFEST.in
README.md
setup.py
PEAS.egg-info/PKG-INFO
PEAS.egg-info/SOURCES.txt
PEAS.egg-info/dependency_links.txt
PEAS.egg-info/not-zip-safe
PEAS.egg-info/requires.txt
PEAS.egg-info/top_level.txt
peas/__init__.py
peas/arrayfuncs.py
peas/choosing.py
peas/constants.py
peas/genomic_regions.py
peas/interface.py
peas/my_array_funcs.c
peas/my_array_funcs.h
peas/region_stats.py
peas/scoring.py
peas/scoring_funcs_c.c
peas/scoring_funcs_cython.c
peas/scoring_funcs_cython.cpython-36m-x86_64-linux-gnu.so
peas/scoring_funcs_cython.pyx
peas/__pycache__/__init__.cpython-36.pyc
peas/__pycache__/arrayfuncs.cpython-36.pyc
peas/__pycache__/choosing.cpython-36.pyc
peas/__pycache__/constants.cpython-36.pyc
peas/__pycache__/genomic_regions.cpython-36.pyc
peas/__pycache__/interface.cpython-36.pyc
peas/__pycache__/region_stats.cpython-36.pyc
peas/__pycache__/scoring.cpython-36.pyc
peas/__pycache__/utilities.cpython-36.pyc
scripts/genomic_peas.py