Metadata-Version: 1.2
Name: PEAS
Version: 0.2.0
Summary: Proximal Enrichment By Approximated Sampling
Home-page: https://github.com/phageghost/PEAS
Author: Dylan Skola
Author-email: peas@phageghost.net
License: MIT
Platform: UNKNOWN
Classifier: Programming Language :: Python :: 3
Classifier: License :: OSI Approved :: MIT License
Classifier: Operating System :: OS Independent
Requires-Python: >=3.6
